[

 {
   "FIELD1": "Store",
   "FIELD2": "Store Name",
   "FIELD3": "# Demand Units",
   "FIELD4": "Demand Sales",
   "FIELD5": "Fulfilled Units",
   "FIELD6": "Fulfilled Sales",
   "FIELD7": "Avg. Item",
   "FIELD8": "% $ Fulfilled",
   "FIELD9": "Retrn/Exchgn $",
   "FIELD10": "% Return $",
   "FIELD11": "Net Sales",
   "FIELD12": "# Custs",
   "FIELD13": "Sales",
   "FIELD14": "# Custs",
   "FIELD15": "Sales"
 },
 {
   "FIELD1": "3",
   "FIELD2": "NORTH",
   "FIELD3": "34",
   "FIELD4": "$690.19",
   "FIELD5": "11",
   "FIELD6": "$245.61",
   "FIELD7": "$22.33",
   "FIELD8": "35.6%",
   "FIELD9": "0",
   "FIELD10": "0.0%",
   "FIELD11": "$245.61",
   "FIELD12": "",
   "FIELD13": "",
   "FIELD14": "",
   "FIELD15": ""
 },
 {
   "FIELD1": "4",
   "FIELD2": "EAST",
   "FIELD3": "57",
   "FIELD4": "$599.30",
   "FIELD5": "40",
   "FIELD6": "$616.36",
   "FIELD7": "$15.41",
   "FIELD8": "102.8%",
   "FIELD9": "(58.5)",
   "FIELD10": "-9.5%",
   "FIELD11": "$557.86",
   "FIELD12": "",
   "FIELD13": "",
   "FIELD14": "",
   "FIELD15": ""
 },
 {
   "FIELD1": "5",
   "FIELD2": "LEBANON",
   "FIELD3": "45",
   "FIELD4": "$752.10",
   "FIELD5": "21",
   "FIELD6": "$387.59",
   "FIELD7": "$18.46",
   "FIELD8": "51.5%",
   "FIELD9": "(66.08)",
   "FIELD10": "-17.0%",
   "FIELD11": "$321.51",
   "FIELD12": "",
   "FIELD13": "",
   "FIELD14": "",
   "FIELD15": ""
 },
 {
   "FIELD1": "6",
   "FIELD2": "POTTSVILLE",
   "FIELD3": "20",
   "FIELD4": "$652.44",
   "FIELD5": "4",
   "FIELD6": "$139.96",
   "FIELD7": "$34.99",
   "FIELD8": "21.5%",
   "FIELD9": "(92.09)",
   "FIELD10": "-65.8%",
   "FIELD11": "$47.87",
   "FIELD12": "1",
   "FIELD13": "$16.74",
   "FIELD14": "",
   "FIELD15": "35.0%"
 },
 {
   "FIELD1": "7",
   "FIELD2": "SUNBURY",
   "FIELD3": "4",
   "FIELD4": "$91.21",
   "FIELD5": "1",
   "FIELD6": "$71.99",
   "FIELD7": "$71.99",
   "FIELD8": "78.9%",
   "FIELD9": "0",
   "FIELD10": "0.0%",
   "FIELD11": "$71.99",
   "FIELD12": "",
   "FIELD13": "",
   "FIELD14": "",
   "FIELD15": ""
 },
 {
   "FIELD1": "8",
   "FIELD2": "WILKES BARRE",
   "FIELD3": "34",
   "FIELD4": "$616.64",
   "FIELD5": "24",
   "FIELD6": "$407.36",
   "FIELD7": "$16.97",
   "FIELD8": "66.1%",
   "FIELD9": "0",
   "FIELD10": "0.0%",
   "FIELD11": "$407.36",
   "FIELD12": "",
   "FIELD13": "",
   "FIELD14": "",
   "FIELD15": ""
 },
 {
   "FIELD1": "9",
   "FIELD2": "HAZLETON",
   "FIELD3": "20",
   "FIELD4": "$346.95",
   "FIELD5": "5",
   "FIELD6": "$176.47",
   "FIELD7": "$35.29",
   "FIELD8": "50.9%",
   "FIELD9": "11.99",
   "FIELD10": "6.8%",
   "FIELD11": "$188.46",
   "FIELD12": "",
   "FIELD13": "",
   "FIELD14": "",
   "FIELD15": ""
 },
 {
   "FIELD1": "10",
   "FIELD2": "DOVER",
   "FIELD3": "26",
   "FIELD4": "$405.62",
   "FIELD5": "16",
   "FIELD6": "$343.23",
   "FIELD7": "$21.45",
   "FIELD8": "84.6%",
   "FIELD9": "(21.2)",
   "FIELD10": "-6.2%",
   "FIELD11": "$322.03",
   "FIELD12": "",
   "FIELD13": "",
   "FIELD14": "",
   "FIELD15": ""
 },
 {
   "FIELD1": "11",
   "FIELD2": "BINGHAMTON",
   "FIELD3": "18",
   "FIELD4": "$370.54",
   "FIELD5": "1",
   "FIELD6": "$39.41",
   "FIELD7": "$39.41",
   "FIELD8": "10.6%",
   "FIELD9": "0",
   "FIELD10": "0.0%",
   "FIELD11": "$39.41",
   "FIELD12": "",
   "FIELD13": "",
   "FIELD14": "",
   "FIELD15": ""
 },
 {
   "FIELD1": "12",
   "FIELD2": "CAMP HILL",
   "FIELD3": "38",
   "FIELD4": "$596.35",
   "FIELD5": "13",
   "FIELD6": "$244.77",
   "FIELD7": "$18.83",
   "FIELD8": "41.0%",
   "FIELD9": "0",
   "FIELD10": "0.0%",
   "FIELD11": "$244.77",
   "FIELD12": "",
   "FIELD13": "",
   "FIELD14": "",
   "FIELD15": ""
 },
 {
   "FIELD1": "14",
   "FIELD2": "COLONIAL PARK",
   "FIELD3": "13",
   "FIELD4": "$184.46",
   "FIELD5": "",
   "FIELD6": "",
   "FIELD7": "",
   "FIELD8": "",
   "FIELD9": "",
   "FIELD10": "",
   "FIELD11": "",
   "FIELD12": "",
   "FIELD13": "",
   "FIELD14": "",
   "FIELD15": ""
 },
 {
   "FIELD1": "16",
   "FIELD2": "WILMINGTON",
   "FIELD3": "126",
   "FIELD4": "$1,614.85",
   "FIELD5": "87",
   "FIELD6": "$1,054.64",
   "FIELD7": "$12.12",
   "FIELD8": "65.3%",
   "FIELD9": "(9.99)",
   "FIELD10": "-0.9%",
   "FIELD11": "$1,044.65",
   "FIELD12": "1",
   "FIELD13": "$57.97",
   "FIELD14": "100.0%",
   "FIELD15": "5.5%"
 },
 {
   "FIELD1": "17",
   "FIELD2": "LANCASTER",
   "FIELD3": "50",
   "FIELD4": "$851.28",
   "FIELD5": "11",
   "FIELD6": "$422.63",
   "FIELD7": "$38.42",
   "FIELD8": "49.6%",
   "FIELD9": "0",
   "FIELD10": "0.0%",
   "FIELD11": "$422.63",
   "FIELD12": "2",
   "FIELD13": "$81.71",
   "FIELD14": "",
   "FIELD15": "19.3%"
 },
 {
   "FIELD1": "18",
   "FIELD2": "ATLANTIC CITY",
   "FIELD3": "38",
   "FIELD4": "$728.05",
   "FIELD5": "17",
   "FIELD6": "$447.08",
   "FIELD7": "$26.30",
   "FIELD8": "61.4%",
   "FIELD9": "(39.99)",
   "FIELD10": "-8.9%",
   "FIELD11": "$407.09",
   "FIELD12": "3",
   "FIELD13": "$134.48",
   "FIELD14": "",
   "FIELD15": "33.0%"
 },
 {
   "FIELD1": "19",
   "FIELD2": "YORK",
   "FIELD3": "63",
   "FIELD4": "$951.34",
   "FIELD5": "21",
   "FIELD6": "$389.91",
   "FIELD7": "$18.57",
   "FIELD8": "41.0%",
   "FIELD9": "(8.49)",
   "FIELD10": "-2.2%",
   "FIELD11": "$381.42",
   "FIELD12": "1",
   "FIELD13": "$46.73",
   "FIELD14": "",
   "FIELD15": "12.3%"
 },
 {
   "FIELD1": "20",
   "FIELD2": "EASTWOOD",
   "FIELD3": "43",
   "FIELD4": "$754.54",
   "FIELD5": "23",
   "FIELD6": "$340.77",
   "FIELD7": "$14.82",
   "FIELD8": "45.2%",
   "FIELD9": "(3.75)",
   "FIELD10": "-1.1%",
   "FIELD11": "$337.02",
   "FIELD12": "2",
   "FIELD13": "$184.33",
   "FIELD14": "200.0%",
   "FIELD15": "54.7%"
 },
 {
   "FIELD1": "21",
   "FIELD2": "CLARKSBURG",
   "FIELD3": "",
   "FIELD4": "",
   "FIELD5": "",
   "FIELD6": "",
   "FIELD7": "",
   "FIELD8": "",
   "FIELD9": "",
   "FIELD10": "",
   "FIELD11": "",
   "FIELD12": "",
   "FIELD13": "",
   "FIELD14": "",
   "FIELD15": ""
 },
 {
   "FIELD1": "28",
   "FIELD2": "LEHIGH VALLEY",
   "FIELD3": "75",
   "FIELD4": "$1,115.45",
   "FIELD5": "17",
   "FIELD6": "$308.75",
   "FIELD7": "$18.16",
   "FIELD8": "27.7%",
   "FIELD9": "(56.23)",
   "FIELD10": "-18.2%",
   "FIELD11": "$252.52",
   "FIELD12": "6",
   "FIELD13": "$595.09",
   "FIELD14": "300.0%",
   "FIELD15": "235.7%"
 },
 {
   "FIELD1": "33",
   "FIELD2": "DEPTFORD",
   "FIELD3": "91",
   "FIELD4": "$1,525.89",
   "FIELD5": "68",
   "FIELD6": "$1,237.50",
   "FIELD7": "$18.20",
   "FIELD8": "81.1%",
   "FIELD9": "(52.47)",
   "FIELD10": "-4.2%",
   "FIELD11": "$1,185.03",
   "FIELD12": "4",
   "FIELD13": "$430.20",
   "FIELD14": "",
   "FIELD15": "36.3%"
 },
 {
   "FIELD1": "41",
   "FIELD2": "WOODBRIDGE",
   "FIELD3": "48",
   "FIELD4": "$964.78",
   "FIELD5": "18",
   "FIELD6": "$312.83",
   "FIELD7": "$17.38",
   "FIELD8": "32.4%",
   "FIELD9": "0",
   "FIELD10": "0.0%",
   "FIELD11": "$312.83",
   "FIELD12": "3",
   "FIELD13": "$137.76",
   "FIELD14": "300.0%",
   "FIELD15": "44.0%"
 },
 {
   "FIELD1": "42",
   "FIELD2": "WHITE MARSH",
   "FIELD3": "36",
   "FIELD4": "$882.97",
   "FIELD5": "15",
   "FIELD6": "$313.12",
   "FIELD7": "$20.87",
   "FIELD8": "35.5%",
   "FIELD9": "0",
   "FIELD10": "0.0%",
   "FIELD11": "$313.12",
   "FIELD12": "",
   "FIELD13": "",
   "FIELD14": "",
   "FIELD15": ""
 },
 {
   "FIELD1": "43",
   "FIELD2": "OHIO VALLEY",
   "FIELD3": "8",
   "FIELD4": "$101.84",
   "FIELD5": "5",
   "FIELD6": "$73.95",
   "FIELD7": "$14.79",
   "FIELD8": "72.6%",
   "FIELD9": "(39.98)",
   "FIELD10": "-54.1%",
   "FIELD11": "$33.97",
   "FIELD12": "1",
   "FIELD13": "$25.72",
   "FIELD14": "100.0%",
   "FIELD15": "75.7%"
 },
 {
   "FIELD1": "44",
   "FIELD2": "MERIDEN",
   "FIELD3": "20",
   "FIELD4": "$427.26",
   "FIELD5": "25",
   "FIELD6": "$326.71",
   "FIELD7": "$13.07",
   "FIELD8": "76.5%",
   "FIELD9": "(69.96)",
   "FIELD10": "-21.4%",
   "FIELD11": "$256.75",
   "FIELD12": "3",
   "FIELD13": "$137.17",
   "FIELD14": "",
   "FIELD15": "53.4%"
 },
 {
   "FIELD1": "46",
   "FIELD2": "UTICA",
   "FIELD3": "21",
   "FIELD4": "$707.43",
   "FIELD5": "2",
   "FIELD6": "$46.98",
   "FIELD7": "$23.49",
   "FIELD8": "6.6%",
   "FIELD9": "0",
   "FIELD10": "0.0%",
   "FIELD11": "$46.98",
   "FIELD12": "",
   "FIELD13": "",
   "FIELD14": "",
   "FIELD15": ""
 },
 {
   "FIELD1": "47",
   "FIELD2": "ERIE",
   "FIELD3": "30",
   "FIELD4": "$497.10",
   "FIELD5": "21",
   "FIELD6": "$298.90",
   "FIELD7": "$14.23",
   "FIELD8": "60.1%",
   "FIELD9": "0",
   "FIELD10": "0.0%",
   "FIELD11": "$298.90",
   "FIELD12": "",
   "FIELD13": "",
   "FIELD14": "",
   "FIELD15": ""
 },
 {
   "FIELD1": "48",
   "FIELD2": "MILFORD",
   "FIELD3": "22",
   "FIELD4": "$323.79",
   "FIELD5": "12",
   "FIELD6": "$116.18",
   "FIELD7": "$9.68",
   "FIELD8": "35.9%",
   "FIELD9": "(27.19)",
   "FIELD10": "-23.4%",
   "FIELD11": "$88.99",
   "FIELD12": "3",
   "FIELD13": "$247.19",
   "FIELD14": "300.0%",
   "FIELD15": "277.8%"
 },
 {
   "FIELD1": "49",
   "FIELD2": "PROVIDENCE",
   "FIELD3": "6",
   "FIELD4": "$76.94",
   "FIELD5": "4",
   "FIELD6": "$54.96",
   "FIELD7": "$13.74",
   "FIELD8": "71.4%",
   "FIELD9": "0",
   "FIELD10": "0.0%",
   "FIELD11": "$54.96",
   "FIELD12": "1",
   "FIELD13": "$19.98",
   "FIELD14": "",
   "FIELD15": "36.4%"
 },
 {
   "FIELD1": "50",
   "FIELD2": "SALISBURY",
   "FIELD3": "7",
   "FIELD4": "$151.68",
   "FIELD5": "13",
   "FIELD6": "$189.98",
   "FIELD7": "$14.61",
   "FIELD8": "125.3%",
   "FIELD9": "0",
   "FIELD10": "0.0%",
   "FIELD11": "$189.98",
   "FIELD12": "1",
   "FIELD13": "$223.83",
   "FIELD14": "",
   "FIELD15": "117.8%"
 },
 {
   "FIELD1": "51",
   "FIELD2": "JOHNSTOWN",
   "FIELD3": "38",
   "FIELD4": "$474.65",
   "FIELD5": "8",
   "FIELD6": "$131.75",
   "FIELD7": "$16.47",
   "FIELD8": "27.8%",
   "FIELD9": "0",
   "FIELD10": "0.0%",
   "FIELD11": "$131.75",
   "FIELD12": "",
   "FIELD13": "",
   "FIELD14": "",
   "FIELD15": ""
 },
 {
   "FIELD1": "52",
   "FIELD2": "SCRANTON",
   "FIELD3": "25",
   "FIELD4": "$592.93",
   "FIELD5": "22",
   "FIELD6": "$336.17",
   "FIELD7": "$15.28",
   "FIELD8": "56.7%",
   "FIELD9": "0",
   "FIELD10": "0.0%",
   "FIELD11": "$336.17",
   "FIELD12": "2",
   "FIELD13": "$512.69",
   "FIELD14": "200.0%",
   "FIELD15": "152.5%"
 },
 {
   "FIELD1": "53",
   "FIELD2": "ECHELON",
   "FIELD3": "46",
   "FIELD4": "$956.93",
   "FIELD5": "21",
   "FIELD6": "$473.72",
   "FIELD7": "$22.56",
   "FIELD8": "49.5%",
   "FIELD9": "0",
   "FIELD10": "0.0%",
   "FIELD11": "$473.72",
   "FIELD12": "1",
   "FIELD13": "$100.58",
   "FIELD14": "",
   "FIELD15": "21.2%"
 },
 {
   "FIELD1": "59",
   "FIELD2": "MOORESTOWN",
   "FIELD3": "67",
   "FIELD4": "$1,062.53",
   "FIELD5": "30",
   "FIELD6": "$606.11",
   "FIELD7": "$20.20",
   "FIELD8": "57.0%",
   "FIELD9": "(53.7)",
   "FIELD10": "-8.9%",
   "FIELD11": "$552.41",
   "FIELD12": "6",
   "FIELD13": "$798.07",
   "FIELD14": "",
   "FIELD15": "144.5%"
 },
 {
   "FIELD1": "60",
   "FIELD2": "GRANITE RUN",
   "FIELD3": "52",
   "FIELD4": "$899.94",
   "FIELD5": "25",
   "FIELD6": "$261.31",
   "FIELD7": "$10.45",
   "FIELD8": "29.0%",
   "FIELD9": "(43.46)",
   "FIELD10": "-16.6%",
   "FIELD11": "$217.85",
   "FIELD12": "1",
   "FIELD13": "$8.47",
   "FIELD14": "",
   "FIELD15": "3.9%"
 },
 {
   "FIELD1": "61",
   "FIELD2": "COVENTRY",
   "FIELD3": "50",
   "FIELD4": "$866.57",
   "FIELD5": "40",
   "FIELD6": "$587.80",
   "FIELD7": "$14.70",
   "FIELD8": "67.8%",
   "FIELD9": "(121.23)",
   "FIELD10": "-20.6%",
   "FIELD11": "$466.57",
   "FIELD12": "3",
   "FIELD13": "$120.91",
   "FIELD14": "",
   "FIELD15": "25.9%"
 },
 {
   "FIELD1": "62",
   "FIELD2": "NESHAMINY",
   "FIELD3": "130",
   "FIELD4": "$2,234.04",
   "FIELD5": "42",
   "FIELD6": "$792.14",
   "FIELD7": "$18.86",
   "FIELD8": "35.5%",
   "FIELD9": "(240.56)",
   "FIELD10": "-30.4%",
   "FIELD11": "$551.58",
   "FIELD12": "3",
   "FIELD13": "$176.71",
   "FIELD14": "150.0%",
   "FIELD15": "32.0%"
 },
 {
   "FIELD1": "63",
   "FIELD2": "PLYMOUTH MEETING",
   "FIELD3": "66",
   "FIELD4": "$1,236.10",
   "FIELD5": "32",
   "FIELD6": "$551.80",
   "FIELD7": "$17.24",
   "FIELD8": "44.6%",
   "FIELD9": "(34)",
   "FIELD10": "-6.2%",
   "FIELD11": "$517.80",
   "FIELD12": "2",
   "FIELD13": "$38.94",
   "FIELD14": "",
   "FIELD15": "7.5%"
 },
 {
   "FIELD1": "64",
   "FIELD2": "VINELAND",
   "FIELD3": "29",
   "FIELD4": "$621.33",
   "FIELD5": "21",
   "FIELD6": "$385.99",
   "FIELD7": "$18.38",
   "FIELD8": "62.1%",
   "FIELD9": "(33.96)",
   "FIELD10": "-8.8%",
   "FIELD11": "$352.03",
   "FIELD12": "",
   "FIELD13": "",
   "FIELD14": "",
   "FIELD15": ""
 },
 {
   "FIELD1": "65",
   "FIELD2": "EASTON",
   "FIELD3": "56",
   "FIELD4": "$867.81",
   "FIELD5": "31",
   "FIELD6": "$756.50",
   "FIELD7": "$24.40",
   "FIELD8": "87.2%",
   "FIELD9": "(103.51)",
   "FIELD10": "-13.7%",
   "FIELD11": "$652.99",
   "FIELD12": "4",
   "FIELD13": "$164.31",
   "FIELD14": "",
   "FIELD15": "25.2%"
 },
 {
   "FIELD1": "66",
   "FIELD2": "ALBANY",
   "FIELD3": "86",
   "FIELD4": "$1,153.29",
   "FIELD5": "18",
   "FIELD6": "$315.28",
   "FIELD7": "$17.52",
   "FIELD8": "27.3%",
   "FIELD9": "0",
   "FIELD10": "0.0%",
   "FIELD11": "$315.28",
   "FIELD12": "1",
   "FIELD13": "$37.43",
   "FIELD14": "33.3%",
   "FIELD15": "11.9%"
 },
 {
   "FIELD1": "67",
   "FIELD2": "BEAVER VALLEY",
   "FIELD3": "30",
   "FIELD4": "$557.76",
   "FIELD5": "20",
   "FIELD6": "$374.21",
   "FIELD7": "$18.71",
   "FIELD8": "67.1%",
   "FIELD9": "0",
   "FIELD10": "0.0%",
   "FIELD11": "$374.21",
   "FIELD12": "",
   "FIELD13": "",
   "FIELD14": "",
   "FIELD15": ""
 },
 {
   "FIELD1": "68",
   "FIELD2": "EXTON",
   "FIELD3": "27",
   "FIELD4": "$490.79",
   "FIELD5": "10",
   "FIELD6": "$94.46",
   "FIELD7": "$9.45",
   "FIELD8": "19.2%",
   "FIELD9": "(8.99)",
   "FIELD10": "-9.5%",
   "FIELD11": "$85.47",
   "FIELD12": "2",
   "FIELD13": "$54.19",
   "FIELD14": "",
   "FIELD15": "63.4%"
 },
 {
   "FIELD1": "69",
   "FIELD2": "BUTLER",
   "FIELD3": "17",
   "FIELD4": "$446.91",
   "FIELD5": "1",
   "FIELD6": "$49.99",
   "FIELD7": "$49.99",
   "FIELD8": "11.2%",
   "FIELD9": "0",
   "FIELD10": "0.0%",
   "FIELD11": "$49.99",
   "FIELD12": "",
   "FIELD13": "",
   "FIELD14": "",
   "FIELD15": ""
 },
 {
   "FIELD1": "70",
   "FIELD2": "CLIFTON PARK",
   "FIELD3": "59",
   "FIELD4": "$1,193.10",
   "FIELD5": "9",
   "FIELD6": "$398.17",
   "FIELD7": "$44.24",
   "FIELD8": "33.4%",
   "FIELD9": "(129.98)",
   "FIELD10": "-32.6%",
   "FIELD11": "$268.19",
   "FIELD12": "",
   "FIELD13": "",
   "FIELD14": "",
   "FIELD15": ""
 },
 {
   "FIELD1": "72",
   "FIELD2": "CHRISTIANA",
   "FIELD3": "62",
   "FIELD4": "$944.72",
   "FIELD5": "15",
   "FIELD6": "$246.28",
   "FIELD7": "$16.42",
   "FIELD8": "26.1%",
   "FIELD9": "(33.98)",
   "FIELD10": "-13.8%",
   "FIELD11": "$212.30",
   "FIELD12": "2",
   "FIELD13": "$49.98",
   "FIELD14": "",
   "FIELD15": "23.5%"
 },
 {
   "FIELD1": "73",
   "FIELD2": "MONMOUTH",
   "FIELD3": "11",
   "FIELD4": "$251.40",
   "FIELD5": "",
   "FIELD6": "",
   "FIELD7": "",
   "FIELD8": "",
   "FIELD9": "",
   "FIELD10": "",
   "FIELD11": "",
   "FIELD12": "",
   "FIELD13": "",
   "FIELD14": "",
   "FIELD15": ""
 },
 {
   "FIELD1": "74",
   "FIELD2": "TOMS RIVER",
   "FIELD3": "25",
   "FIELD4": "$557.86",
   "FIELD5": "23",
   "FIELD6": "$375.60",
   "FIELD7": "$16.33",
   "FIELD8": "67.3%",
   "FIELD9": "(14.97)",
   "FIELD10": "-4.0%",
   "FIELD11": "$360.63",
   "FIELD12": "2",
   "FIELD13": "$170.61",
   "FIELD14": "",
   "FIELD15": "47.3%"
 },
 {
   "FIELD1": "75",
   "FIELD2": "BERKSHIRE",
   "FIELD3": "27",
   "FIELD4": "$496.18",
   "FIELD5": "4",
   "FIELD6": "$73.72",
   "FIELD7": "$18.43",
   "FIELD8": "14.9%",
   "FIELD9": "0",
   "FIELD10": "0.0%",
   "FIELD11": "$73.72",
   "FIELD12": "",
   "FIELD13": "",
   "FIELD14": "",
   "FIELD15": ""
 },
 {
   "FIELD1": "76",
   "FIELD2": "WESTMINSTER",
   "FIELD3": "23",
   "FIELD4": "$657.30",
   "FIELD5": "18",
   "FIELD6": "$435.37",
   "FIELD7": "$24.19",
   "FIELD8": "66.2%",
   "FIELD9": "(39.96)",
   "FIELD10": "-9.2%",
   "FIELD11": "$395.41",
   "FIELD12": "2",
   "FIELD13": "$65.69",
   "FIELD14": "200.0%",
   "FIELD15": "16.6%"
 },
 {
   "FIELD1": "77",
   "FIELD2": "FREDERICK",
   "FIELD3": "29",
   "FIELD4": "$495.70",
   "FIELD5": "22",
   "FIELD6": "$335.99",
   "FIELD7": "$15.27",
   "FIELD8": "67.8%",
   "FIELD9": "(59.99)",
   "FIELD10": "-17.9%",
   "FIELD11": "$276.00",
   "FIELD12": "1",
   "FIELD13": "$51.32",
   "FIELD14": "",
   "FIELD15": "18.6%"
 },
 {
   "FIELD1": "79",
   "FIELD2": "ALTOONA",
   "FIELD3": "35",
   "FIELD4": "$666.79",
   "FIELD5": "27",
   "FIELD6": "$467.69",
   "FIELD7": "$17.32",
   "FIELD8": "70.1%",
   "FIELD9": "0",
   "FIELD10": "0.0%",
   "FIELD11": "$467.69",
   "FIELD12": "2",
   "FIELD13": "$175.16",
   "FIELD14": "",
   "FIELD15": "37.5%"
 },
 {
   "FIELD1": "98",
   "FIELD2": "CORPORATE",
   "FIELD3": "",
   "FIELD4": "",
   "FIELD5": "",
   "FIELD6": "",
   "FIELD7": "",
   "FIELD8": "",
   "FIELD9": "",
   "FIELD10": "",
   "FIELD11": "",
   "FIELD12": "",
   "FIELD13": "",
   "FIELD14": "",
   "FIELD15": ""
 },
 {
   "FIELD1": "Overall - Summary",
   "FIELD2": "",
   "FIELD3": "1,983",
   "FIELD4": "$34,705.62",
   "FIELD5": "934",
   "FIELD6": "$16,657.69",
   "FIELD7": "$17.83",
   "FIELD8": "48.0%",
   "FIELD9": "(1,452.22)",
   "FIELD10": "-8.7%",
   "FIELD11": "$15,205.47",
   "FIELD12": "66",
   "FIELD13": "$4,863.96",
   "FIELD14": "244.4%",
   "FIELD15": "32.0%"
 },

]